data533_superman/__init__.py
data533_superman/main.py
data533_superman/administer/Testaccount_promotion.py
data533_superman/administer/Testaccount_promotion1.py
data533_superman/administer/Testinventory_class.py
data533_superman/administer/Testinventory_rollback.py
data533_superman/customer/customer_function.py
data533_superman/customer/test_members.py
data533_superman/customer/test_transactions.py
data533_superman-0.0.2.dist-info/METADATA
data533_superman-0.0.2.dist-info/WHEEL
data533_superman-0.0.2.dist-info/top_level.txt
data533_superman-0.0.2.dist-info/RECORD
